SwiftShejimoshiIos/README.md
SwiftShejimoshiIos/__init__.py
SwiftShejimoshiIos/__main__.py
SwiftShejimoshiIos/file.epub
SwiftShejimoshiIos/index.html
SwiftShejimoshiIos/css/__init__.py
SwiftShejimoshiIos/css/annotations.css
SwiftShejimoshiIos/css/main.css
SwiftShejimoshiIos/css/normalize.css
SwiftShejimoshiIos/css/popup.css
SwiftShejimoshiIos/font/__init__.py
SwiftShejimoshiIos/font/fontello.eot
SwiftShejimoshiIos/font/fontello.svg
SwiftShejimoshiIos/font/fontello.ttf
SwiftShejimoshiIos/font/fontello.woff
SwiftShejimoshiIos/img/__init__.py
SwiftShejimoshiIos/img/annotator-glyph-sprite.png
SwiftShejimoshiIos/img/annotator-icon-sprite.png
SwiftShejimoshiIos/img/apple-touch-icon.png
SwiftShejimoshiIos/img/cancelfullscreen.png
SwiftShejimoshiIos/img/close.png
SwiftShejimoshiIos/img/fullscreen.png
SwiftShejimoshiIos/img/loader.gif
SwiftShejimoshiIos/img/menu-icon.png
SwiftShejimoshiIos/img/save.png
SwiftShejimoshiIos/img/saved.png
SwiftShejimoshiIos/img/settings-s.png
SwiftShejimoshiIos/img/settings.png
SwiftShejimoshiIos/img/star.png
SwiftShejimoshiIos/js/__init__.py
SwiftShejimoshiIos/js/epub.js
SwiftShejimoshiIos/js/epub.min.js
SwiftShejimoshiIos/js/epub.min.map
SwiftShejimoshiIos/js/hooks.min.js
SwiftShejimoshiIos/js/hooks.min.map
SwiftShejimoshiIos/js/reader.js
SwiftShejimoshiIos/js/reader.js.map
SwiftShejimoshiIos/js/reader.min.js
SwiftShejimoshiIos/js/reader.min.map
SwiftShejimoshiIos/js/hooks/__init__.py
SwiftShejimoshiIos/js/hooks/extensions/__init__.py
SwiftShejimoshiIos/js/hooks/extensions/highlight.js
SwiftShejimoshiIos/js/libs/__init__.py
SwiftShejimoshiIos/js/libs/jquery.min.js
SwiftShejimoshiIos/js/libs/localforage.min.js
SwiftShejimoshiIos/js/libs/screenfull.js
SwiftShejimoshiIos/js/libs/screenfull.min.js
SwiftShejimoshiIos/js/libs/zip.min.js
SwiftShejimoshiIos/js/plugins/__init__.py
SwiftShejimoshiIos/js/plugins/hypothesis.js
SwiftShejimoshiIos/js/plugins/search.js
swift_shejimoshi_ios-2024.3.4.0.dist-info/METADATA
swift_shejimoshi_ios-2024.3.4.0.dist-info/WHEEL
swift_shejimoshi_ios-2024.3.4.0.dist-info/entry_points.txt
swift_shejimoshi_ios-2024.3.4.0.dist-info/top_level.txt
swift_shejimoshi_ios-2024.3.4.0.dist-info/RECORD
